mdf_reader/__init__.py
mdf_reader/mdf_blocks.py
mdf_reader/mdf_parser.py
pyMdfReader-0.1.5.dist-info/LICENSE.txt
pyMdfReader-0.1.5.dist-info/METADATA
pyMdfReader-0.1.5.dist-info/WHEEL
pyMdfReader-0.1.5.dist-info/top_level.txt
pyMdfReader-0.1.5.dist-info/RECORD
