Metadata-Version: 2.1
Name: pyMdfReader
Version: 0.1.5
Summary: Read the binary MDF file format
Home-page: https://github.com/eelcovv/pyMdfReader
Author: Eelco van Vliet
Author-email: eelcovv@gmail.com
License: MIT
Project-URL: Documentation, https://pymdfreader.readthedocs.io/en/latest/
Platform: any
Classifier: Development Status :: 4 - Beta
Classifier: Programming Language :: Python
License-File: LICENSE.txt
Requires-Dist: numpy
Requires-Dist: pandas
Requires-Dist: importlib-metadata ; python_version < "3.8"
Provides-Extra: dev
Requires-Dist: pytest ; extra == 'dev'
Requires-Dist: pytest-cov ; extra == 'dev'
Requires-Dist: black ; extra == 'dev'
Requires-Dist: tox ; extra == 'dev'
Requires-Dist: pre-commit ; extra == 'dev'
Provides-Extra: examples
Requires-Dist: matplotlib ; extra == 'examples'
Provides-Extra: notebook
Requires-Dist: seaborn ; extra == 'notebook'
Requires-Dist: jupyter ; extra == 'notebook'
Provides-Extra: testing
Requires-Dist: setuptools ; extra == 'testing'
Requires-Dist: pytest ; extra == 'testing'
Requires-Dist: pytest-cov ; extra == 'testing'
